modelpark/__init__.py
modelpark/modelpark.py
modelpark-0.1.19.dist-info/LICENSE
modelpark-0.1.19.dist-info/METADATA
modelpark-0.1.19.dist-info/WHEEL
modelpark-0.1.19.dist-info/top_level.txt
modelpark-0.1.19.dist-info/RECORD
