Metadata-Version: 2.1
Name: modelpark
Version: 0.1.19
Summary: Versatile solution for sharing apps through secure URLs
Home-page: https://github.com/model-park/modelpark
Author: Veysel Kocaman
Author-email: info@modelpark.app
License: MIT
Keywords: modelpark,deployment,cloud,api
Classifier: Development Status :: 3 - Alpha
Classifier: Intended Audience :: Developers
Classifier: License :: OSI Approved :: MIT License
Classifier: Programming Language :: Python :: 3
Classifier: Programming Language :: Python :: 3.6
Classifier: Programming Language :: Python :: 3.7
Classifier: Programming Language :: Python :: 3.8
Classifier: Programming Language :: Python :: 3.9
Classifier: Programming Language :: Python :: 3.10
Classifier: Programming Language :: Python :: 3.11
Classifier: Programming Language :: Python :: 3.12
License-File: LICENSE
Requires-Dist: requests
